LICENSE
README.md
setup.py
Pseudovisium/__init__.py
Pseudovisium/pseudovisium_generate.py
Pseudovisium/pseudovisium_generate_old.py
Pseudovisium/pseudovisium_merge.py
Pseudovisium/pseudovisium_merge_old.py
Pseudovisium/pseudovisium_qc.py
Pseudovisium.egg-info/PKG-INFO
Pseudovisium.egg-info/SOURCES.txt
Pseudovisium.egg-info/dependency_links.txt
Pseudovisium.egg-info/requires.txt
Pseudovisium.egg-info/top_level.txt